pydolly/__init__.py
pydolly-0.0.1.dev0.dist-info/METADATA
pydolly-0.0.1.dev0.dist-info/WHEEL
pydolly-0.0.1.dev0.dist-info/top_level.txt
pydolly-0.0.1.dev0.dist-info/RECORD
