Metadata-Version: 2.1
Name: pydolly
Version: 0.0.1.dev0
Summary: pydolly - A Slim LLM You Can Train Yourself
Author: Shadow Walker
License: UNKNOWN
Keywords: pydolly
Platform: UNKNOWN
Classifier: Programming Language :: Python :: 3
Classifier: Programming Language :: Python :: 3.8
Classifier: Programming Language :: Python :: 3.9
Classifier: Programming Language :: Python :: 3.10
Requires-Dist: torch
